mingus/__init__.py
mingus/containers/__init__.py
mingus/containers/bar.py
mingus/containers/composition.py
mingus/containers/instrument.py
mingus/containers/mt_exceptions.py
mingus/containers/note.py
mingus/containers/note_container.py
mingus/containers/suite.py
mingus/containers/track.py
mingus/core/__init__.py
mingus/core/chords.py
mingus/core/intervals.py
mingus/core/keys.py
mingus/core/meter.py
mingus/core/mt_exceptions.py
mingus/core/notes.py
mingus/core/progressions.py
mingus/core/scales.py
mingus/core/value.py
mingus/extra/__init__.py
mingus/extra/fft.py
mingus/extra/lilypond.py
mingus/extra/musicxml.py
mingus/extra/tablature.py
mingus/extra/tunings.py
mingus/midi/__init__.py
mingus/midi/fluidsynth.py
mingus/midi/midi_events.py
mingus/midi/midi_file_in.py
mingus/midi/midi_file_out.py
mingus/midi/midi_track.py
mingus/midi/pyfluidsynth.py
mingus/midi/sequencer.py
mingus/midi/sequencer_observer.py
mingus/midi/win32midi.py
mingus/midi/win32midisequencer.py
mingus-0.6.1.data/data/mingus_examples/pygame-drum/pad.png
mingus-0.6.1.data/data/mingus_examples/pygame-drum/pygame-drum.py
mingus-0.6.1.data/data/mingus_examples/pygame-piano/keys.png
mingus-0.6.1.data/data/mingus_examples/pygame-piano/pygame-piano.py
mingus-0.6.1.dist-info/LICENSE
mingus-0.6.1.dist-info/METADATA
mingus-0.6.1.dist-info/WHEEL
mingus-0.6.1.dist-info/top_level.txt
mingus-0.6.1.dist-info/RECORD
